{
  "name": "Jordan Robertson",
  "age": 43,
  "address": {
    "street": "Pufoda Loop",
    "city": "Pupluhen",
    "state": "NE",
    "zip": "14397"
  },
  "contact": {
    "phone": "(982) 937-1388",
    "servicePhone": "800624624"
  },
  "birthday": "1986-03-11T19:24:19.904Z",
  "ip": "98.141.62.12",
  "foo": "bar",
  "profile": {
    "about": "Go zircod arodeb vapuz tul dukuve of johupo corerda hozgocjeb bomriled pis sunha. Ino ni sicijba epumajbec tito pic gidode tasupbo akapafru vus wo kekucen. Vibpu tu vijiglak to biwkemum pojdeg sozizew adcuir enaatuvu zaksiut deg okbiz iwjeon ohuob wohe naliaf owtambo. Iznev ran zojriv huppotkoh fume bad tug za fekze vaklo huz laparotar haumi veskiphu fa.",
    "bio": "Nazi ejvo oci fu we vov suesefa ukuvesa inamuw ofanilo runuz ilomivudo zubma penbesle je fu. Pufoj lozuneve henkabiwu wowauje mo lujupiza buovri ketuppeh en bu ihe sipe. Ru wa dafuhuv neus tum piscac walira puza onisulil vanbe ud wiknemdak vehtuevu ne ibawuot."
  },
  "apiKey": "7e46518a48df7538b80cdb5de955dcba46e0a13a80f51f90b2b8ddb485f9999d",
  "currency": {
    "code": "GBP",
    "name": "United Kingdom Pound"
  }
}